anabel/__init__.py
anabel/_anabel.c
anabel/aisc.py
anabel/analysis.py
anabel/assemble.py
anabel/autodiff.py
anabel/backend.py
anabel/elements.py
anabel/graphics.py
anabel/matrices.py
anabel/opensees.py
anabel/sections.py
anabel/template.py
anabel/transient.py
anabel-0.0.11.dist-info/METADATA
anabel-0.0.11.dist-info/WHEEL
anabel-0.0.11.dist-info/top_level.txt
anabel-0.0.11.dist-info/RECORD
