Metadata-Version: 2.1
Name: anabel
Version: 0.0.11
Summary: An end to end differentiable finite element framework.
Home-page: https://claudioperez.github.io/anabel
Author: Claudio M. Perez
Author-email: claudio_perez@berkeley.edu
License: UNKNOWN
Project-URL: Documentation, https://claudioperez.github.io/anabel
Project-URL: Changelog, https://github.com/claudioperez/anabel/blob/master/CHANGELOG.md
Project-URL: Issue Tracker, https://github.com/claudioperez/anabel/issues
Platform: UNKNOWN
Classifier: Development Status :: 2 - Pre-Alpha
Classifier: Intended Audience :: Developers
Classifier: Operating System :: Unix
Classifier: Operating System :: POSIX
Classifier: Operating System :: Microsoft :: Windows
Classifier: Programming Language :: Python
Classifier: Programming Language :: Python :: 3
Classifier: Programming Language :: Python :: 3.7
Classifier: Programming Language :: Python :: 3.8
Requires-Python: >=3.7
Requires-Dist: jax
Requires-Dist: jaxlib
Requires-Dist: numpy
Requires-Dist: pandoc
Requires-Dist: matplotlib
Requires-Dist: scipy
Requires-Dist: anon
Requires-Dist: meshio
Requires-Dist: pandas
Provides-Extra: backends
Requires-Dist: jaxlib (>0.1.51,~=0.1) ; extra == 'backends'
Requires-Dist: jax (>0.1.72,~=0.1) ; extra == 'backends'
Provides-Extra: interact
Requires-Dist: ipyvtklink ; extra == 'interact'
Requires-Dist: pyvista ; extra == 'interact'
Provides-Extra: jax
Requires-Dist: jax (>0.1.72,~=0.1) ; extra == 'jax'
Requires-Dist: jaxlib (>0.1.51,~=0.1) ; extra == 'jax'
